yamltk/__init__.py
yamltk/yamltk.py
yamltk-0.0.1.dist-info/METADATA
yamltk-0.0.1.dist-info/WHEEL
yamltk-0.0.1.dist-info/licenses/LICENSE
yamltk-0.0.1.dist-info/RECORD
