Metadata-Version: 2.4
Name: yamltk
Version: 0.0.1
Summary: A utility for building Tkinter widget trees from YAML files.
Project-URL: Homepage, https://github.com/yannprada/yaml_tkinter
Project-URL: Issues, https://github.com/yannprada/yaml_tkinter/issues
Author-email: Yannick Pradayrol <pradayrol.yannick@gmail.com>
License-Expression: GPL-3.0-only
License-File: LICENSE
Classifier: Operating System :: OS Independent
Classifier: Programming Language :: Python :: 3
Requires-Python: >=3.13.3
Requires-Dist: pyyaml>=6.0.2
